{"isLogin":true,"count":95285,"pageTotal":3812,"userInfo":[{"uid":147986539,"realUid":148986539,"nickname":"老妹子","sex":"女","sexValue":"f","randAttr":"formal","marriage":"离异","height":"160","education":"大专","income":null,"work_location":"东莞","work_sublocation":"东莞","age":49,"image":"http://images1.jyimg.com/w4/global/i/yzphykj_f.jpg","count":"95243","online":0,"randTag":"<span>55公斤</span><span>O型血</span>","randListTag":"<span>160cm</span><span>55公斤</span><span>汉族</span><span>O型血</span>","userIcon":"<i title=手机认证 class=tel></i><i title=星级会员 class=level></i>","helloUrl":"http://www.jiayuan.com/msg/hello.php?type=20&randomfrom=4&uhash=e1fd7b398cad7f0e5165469ad5b6e490","sendMsgUrl":"http://www.jiayuan.com/msg/send.php?uhash=e1fd7b398cad7f0e5165469ad5b6e490","shortnote":"上佳缘唯一的目的就是想给自己找个伴，找份寄托，做个完整女人，本人一切真实，真诚，找业务的，发展下线的，介绍理财的，请绕道，谢谢！...","matchCondition":"46-56岁,160-185cm,有照片,离异、丧偶"},{"uid":147882414,"realUid":148882414,"nickname":"馨玉","sex":"女","sexValue":"f","randAttr":"formal","marriage":"离异","height":"157","education":"大专","income":null,"work_location":"佛山","work_sublocation":"佛山","age":38,"image":"http://at3.jyimg.com/66/b9/e4614c77f43c7aa694446da7c35b/e4614c77f_3_avatar_p.jpg","count":"95243","online":0,"randTag":"<span>157cm</span><span>大专</span>","randListTag":"<span>157cm</span><span>55公斤</span><span>汉族</span><span>大专</span>","userIcon":"<i title=手机认证 class=tel></i>","helloUrl":"http://www.jiayuan.com/msg/hello.php?type=20&randomfrom=4&uhash=66e4614c77f43c7aa694446da7c35bb9","sendMsgUrl":"http://www.jiayuan.com/msg/send.php?uhash=66e4614c77f43c7aa694446da7c35bb9","shortnote":"我的过去，你来不及参与，但我的未来，一定要有你参与！ &lt;/div&gt;...","matchCondition":"34-50岁,157-182cm,有照片,山西"},{"uid":147873122,"realUid":148873122,"nickname":"子佳","sex":"女","sexValue":"f","randAttr":"formal","marriage":"离异","height":"168","education":"大专","income":null,"work_location":"珠海","work_sublocation":"珠海","age":55,"image":"http://at3.jyimg.com/6b/49/bdb82c8b2a2f807c9030ca9047a0/bdb82c8b2_7_avatar_p.jpg","count":"95243","online":1,"randTag":"<span>大专</span><span>O型血</span>","randListTag":"<span>属兔</span><span>汉族</span><span>大专</span><span>金牛座</span>","userIcon":"<i title=在线 class=online></i><i title=手机认证 class=tel></i>","helloUrl":"http://www.jiayuan.com/msg/hello.php?type=20&randomfrom=4&uhash=6bbdb82c8b2a2f807c9030ca9047a049","sendMsgUrl":"http://www.jiayuan.com/msg/send.php?uhash=6bbdb82c8b2a2f807c9030ca9047a049","shortnote":"等一个知心爱人，不求生死契阔，只愿共渡余生。...","matchCondition":"50-60岁,175-185cm,本科,有照片,离异、丧偶,上海"},{"uid":147865058,"realUid":148865058,"nickname":"蒹葭无霜","sex":"女","sexValue":"f","randAttr":"formal","marriage":"离异","height":"164","education":"本科","income":null,"work_location":"广州","work_sublocation":"广州","age":39,"image":"http://at2.jyimg.com/59/14/ba6e4ebbc419af602cdaf2ee0cf6/ba6e4ebbc_2_avatar_p.jpg","count":"95243","online":0,"randTag":"<span>有房</span><span>双子座</span>","randListTag":"<span>有房</span><span>属羊</span><span>164cm</span><span>50公斤</span>","userIcon":"<i title=手机认证 class=tel></i>","helloUrl":"http://www.jiayuan.com/msg/hello.php?type=20&randomfrom=4&uhash=59ba6e4ebbc419af602cdaf2ee0cf614","sendMsgUrl":"http://www.jiayuan.com/msg/send.php?uhash=59ba6e4ebbc419af602cdaf2ee0cf614","shortnote":"真诚寻找一位同样真诚靠谱的先生认真经营下半生，非诚勿扰。        我很难撩，不玩情感游戏。        打猎的，请走开。        红娘老师谢谢你们的热情，我不骗不抢真…","matchCondition":"36-45岁,170-185cm,本科,有照片,未婚、离异,广东,广州"},{"uid":147753069,"realUid":148753069,"nickname":"璇","sex":"女","sexValue":"f","randAttr":"formal","marriage":"未婚","height":"169","education":"高中中专及以下","income":null,"work_location":"深圳","work_sublocation":"深圳","age":34,"image":"http://at3.jyimg.com/65/4f/b57b41a396d3a58e8deccb1442b2/b57b41a39_3_avatar_p.jpg","count":"95243","online":0,"randTag":"<span>租房</span><span>未婚</span>","randListTag":"<span>169cm</span><span>汉族</span><span>未婚</span><span>中专</span>","userIcon":"<i title=手机认证 class=tel></i>","helloUrl":"http://www.jiayuan.com/msg/hello.php?type=20&randomfrom=4&uhash=65b57b41a396d3a58e8deccb1442b24f","sendMsgUrl":"http://www.jiayuan.com/msg/send.php?uhash=65b57b41a396d3a58e8deccb1442b24f","shortnote":"我是一个简单少根筋的，一个感情、感觉迟钝的潮汕的女孩，等待着真心找过日子的那他，我以鼓起勇气来了，你在哪...","matchCondition":"31-39岁,174-194cm,有照片,广东,深圳"},{"uid":147678695,"realUid":148678695,"nickname":"winnie","sex":"女","sexValue":"f","randAttr":"formal","marriage":"离异","height":"155","education":"高中中专及以下","income":null,"work_location":"东莞","work_sublocation":"东莞","age":39,"image":"http://at2.jyimg.com/98/51/f0cd7c124c87008aa35b4d169571/f0cd7c124_2_avatar_p.jpg","count":"95243","online":0,"randTag":"<span>48公斤</span><span>中专</span>","randListTag":"<span>有车</span><span>有房</span><span>中专</span><span>射手座</span>","userIcon":"<i title=手机认证 class=tel></i>","helloUrl":"http://www.jiayuan.com/msg/hello.php?type=20&randomfrom=4&uhash=98f0cd7c124c87008aa35b4d16957151","sendMsgUrl":"http://www.jiayuan.com/msg/send.php?uhash=98f0cd7c124c87008aa35b4d16957151","shortnote":"让我为你戴你上银白色的钻戒，让我为你穿上白色的礼服，想为早起的你挤牙膏，想为晚起的你做早餐，与你在夕阳下散步，让我守在你的身边一生一世。...","matchCondition":"36-44岁,155-180cm,有照片,未婚、离异,广东,东莞"},{"uid":147734462,"realUid":148734462,"nickname":"沐浴晴朗","sex":"女","sexValue":"f","randAttr":"formal","marriage":"离异","height":"161","education":"硕士","income":null,"work_location":"茂名","work_sublocation":"茂名","age":31,"image":"http://at3.jyimg.com/e7/51/8c52bbbcce5e60e68d2f52c59510/8c52bbbcc_1_avatar_p.jpg","count":"95243","online":0,"randTag":"<span>161cm</span><span>O型血</span>","randListTag":"<span>有房</span><span>161cm</span><span>硕士</span><span>O型血</span>","userIcon":"<i title=手机认证 class=tel></i><i title=佳缘特权 class=gjhy></i>","helloUrl":"http://www.jiayuan.com/msg/hello.php?type=20&randomfrom=4&uhash=e78c52bbbcce5e60e68d2f52c5951051","sendMsgUrl":"http://www.jiayuan.com/msg/send.php?uhash=e78c52bbbcce5e60e68d2f52c5951051","shortnote":"首先，非常感谢您的关注。现在在广东茂名从事教育行业，也有回老家的打算，其实只要人对了，国外也没问题。        关于我：我认为，人最重要的品质是内心深处的善良，只有这样，做人做…","matchCondition":"29-36岁,161-186cm,本科以上,有照片,云南,昆明"},{"uid":147768875,"realUid":148768875,"nickname":"好心情","sex":"女","sexValue":"f","randAttr":"formal","marriage":"未婚","height":"158","education":"大专","income":null,"work_location":"深圳","work_sublocation":"深圳","age":35,"image":"http://at1.jyimg.com/ce/fa/b3c23272d80673f7cbe5fb4fcbe7/b3c23272d_2_avatar_p.jpg","count":"95243","online":1,"randTag":"<span>属鼠</span><span>大专</span>","randListTag":"<span>158cm</span><span>未婚</span><span>O型血</span><span>水瓶座</span>","userIcon":"<i title=在线 class=online></i><i title=手机认证 class=tel></i>","helloUrl":"http://www.jiayuan.com/msg/hello.php?type=20&randomfrom=4&uhash=ceb3c23272d80673f7cbe5fb4fcbe7fa","sendMsgUrl":"http://www.jiayuan.com/msg/send.php?uhash=ceb3c23272d80673f7cbe5fb4fcbe7fa","shortnote":"也许世界很复杂，但我希望生活简单化，单纯化。 世界无完美的人，完美的人也看不上不完美的我。 所以，我将世界中纷繁复杂的品行在乱序中粗粗勾画，形成我所追求的那个他。 善良、包容、 才…","matchCondition":"31-38岁,168-176cm,大专,有照片,广东,深圳"},{"uid":147868677,"realUid":148868677,"nickname":"Una","sex":"女","sexValue":"f","randAttr":"formal","marriage":"未婚","height":"163","education":"本科","income":null,"work_location":"深圳","work_sublocation":"深圳","age":27,"image":"http://at3.jyimg.com/e2/a5/80d47914c8cb02720ca61e59e547/80d47914c_12_avatar_p.jpg","count":"95243","online":0,"randTag":"<span>汉族</span><span>本科</span>","randListTag":"<span>汉族</span><span>未婚</span><span>本科</span><span>天蝎座</span>","userIcon":"<i title=手机认证 class=tel></i><i title=看信包月 class=kxby></i>","helloUrl":"http://www.jiayuan.com/msg/hello.php?type=20&randomfrom=4&uhash=e280d47914c8cb02720ca61e59e547a5","sendMsgUrl":"http://www.jiayuan.com/msg/send.php?uhash=e280d47914c8cb02720ca61e59e547a5","shortnote":"桃之夭夭        灼灼其华        之子于归        宜其家室        甘之如饴        弃之如敝        喜马拉雅账号 清水GF        爱好者入...","matchCondition":"27-34岁,173-188cm,本科,有照片,未婚,广东,深圳"},{"uid":147690384,"realUid":148690384,"nickname":"佳缘会员","sex":"女","sexValue":"f","randAttr":"formal","marriage":"未婚","height":"156","education":"硕士","income":null,"work_location":"深圳","work_sublocation":"深圳","age":48,"image":"http://images1.jyimg.com/w4/global/i/yzphykj_f.jpg","count":"95243","online":1,"randTag":"<span>B型血</span><span>天蝎座</span>","randListTag":"<span>属狗</span><span>156cm</span><span>50公斤</span><span>硕士</span>","userIcon":"<i title=在线 class=online></i><i title=手机认证 class=tel></i>","helloUrl":"http://www.jiayuan.com/msg/hello.php?type=20&randomfrom=4&uhash=4abc05063a556aaa2810b6fc870bcd3a","sendMsgUrl":"http://www.jiayuan.com/msg/send.php?uhash=4abc05063a556aaa2810b6fc870bcd3a","shortnote":"因为求学工作一直独自东奔西跑，再加上被动慢热等等，所以延误至今。希望借此平台能有幸找到一位婚姻、家庭、生活观念类似、看清生活的真相后依然热爱生活、可靠实在的男士，互相包容、彼此欣赏…","matchCondition":"45-53岁,本科,有照片,广东,深圳"},{"uid":147925360,"realUid":148925360,"nickname":"墨玉","sex":"女","sexValue":"f","randAttr":"formal","marriage":"未婚","height":"164","education":"本科","income":null,"work_location":"广州","work_sublocation":"广州","age":27,"image":"http://images1.jyimg.com/w4/global/i/yzphykj_f.jpg","count":"95243","online":0,"randTag":"<span>属羊</span><span>164cm</span>","randListTag":"<span>属羊</span><span>汉族</span><span>未婚</span><span>本科</span>","userIcon":"<i title=手机认证 class=tel></i><i title=佳缘特权 class=gjhy></i>","helloUrl":"http://www.jiayuan.com/msg/hello.php?type=20&randomfrom=4&uhash=909a048809891b6a250fab458f6da91c","sendMsgUrl":"http://www.jiayuan.com/msg/send.php?uhash=909a048809891b6a250fab458f6da91c","shortnote":"我来自中部城市，南方菇凉，金融本科，性格偏活泼～喜欢看书、研究美食、略懂钢琴、热爱大自然～有自己的小梦想，但是家庭和亲情会放首位，愿做最好的支持者～        希望未来的他：靠…","matchCondition":"25-38岁,170-188cm,大专以上,有照片,未婚,广东,广州"},{"uid":148016596,"realUid":149016596,"nickname":"香舍百合","sex":"女","sexValue":"f","randAttr":"formal","marriage":"离异","height":"160","education":"大专","income":null,"work_location":"广州","work_sublocation":"广州","age":35,"image":"http://images1.jyimg.com/w4/global/i/yzphykj_f.jpg","count":"95243","online":0,"randTag":"<span>属猪</span><span>160cm</span>","randListTag":"<span>属猪</span><span>160cm</span><span>大专</span><span>巨蟹座</span>","userIcon":"<i title=手机认证 class=tel></i>","helloUrl":"http://www.jiayuan.com/msg/hello.php?type=20&randomfrom=4&uhash=0ebf9adff90fb063024c5f09b177b225","sendMsgUrl":"http://www.jiayuan.com/msg/send.php?uhash=0ebf9adff90fb063024c5f09b177b225","shortnote":"回家 相亲&amp;lt;br /&amp;gt;愿好运...","matchCondition":"35-39岁,160-177cm,大专,有照片,未婚、离异"},{"uid":147798782,"realUid":148798782,"nickname":"期待缘份","sex":"女","sexValue":"f","randAttr":"formal","marriage":"离异","height":"160","education":"本科","income":null,"work_location":"深圳","work_sublocation":"深圳","age":61,"image":"http://images1.jyimg.com/w4/global/i/yzphykj_f.jpg","count":"95243","online":0,"randTag":"<span>58公斤</span><span>狮子座</span>","randListTag":"<span>有房</span><span>属鸡</span><span>汉族</span><span>本科</span>","userIcon":"<i title=手机认证 class=tel></i>","helloUrl":"http://www.jiayuan.com/msg/hello.php?type=20&randomfrom=4&uhash=8c7b5369954581191b71f82e15d8b716","sendMsgUrl":"http://www.jiayuan.com/msg/send.php?uhash=8c7b5369954581191b71f82e15d8b716","shortnote":"这一生，牵她的手爱了，就要牢牢地，牢牢地靠近，不要在茫茫人海中丢失了彼此。还是，你是你，我是我，互不相欠，各奔幸福。&lt;BR&gt;&lt;BR&gt;...","matchCondition":"63-78岁,166-191cm,有照片,广东,深圳"},{"uid":147815299,"realUid":148815299,"nickname":"水美人","sex":"女","sexValue":"f","randAttr":"formal","marriage":"离异","height":"166","education":"本科","income":null,"work_location":"深圳","work_sublocation":"深圳","age":56,"image":"http://at4.jyimg.com/bc/62/a545b301d2ef8aa391c2e1bd0e62/a545b301d_4_avatar_p.jpg","count":"95243","online":0,"randTag":"<span>本科</span><span>B型血</span>","randListTag":"<span>属兔</span><span>70公斤</span><span>本科</span><span>水瓶座</span>","userIcon":"<i title=手机认证 class=tel></i>","helloUrl":"http://www.jiayuan.com/msg/hello.php?type=20&randomfrom=4&uhash=bca545b301d2ef8aa391c2e1bd0e6262","sendMsgUrl":"http://www.jiayuan.com/msg/send.php?uhash=bca545b301d2ef8aa391c2e1bd0e6262","shortnote":"我爱你是我的自己的事，所以你也许不知道我的存在。但如果遇见那个你，我希望不只是我爱你，而是在一起。有你的日子，阳光明媚，没你的日子，人生灰暗。...","matchCondition":"54-64岁,170-180cm,有照片,美国"},{"uid":147858310,"realUid":148858310,"nickname":"sophie","sex":"女","sexValue":"f","randAttr":"formal","marriage":"未婚","height":"163","education":"大专","income":null,"work_location":"惠州","work_sublocation":"惠州","age":36,"image":"http://at2.jyimg.com/54/aa/63c9cd025182fbde91179e491cbe/63c9cd025_8_avatar_p.jpg","count":"95243","online":1,"randTag":"<span>汉族</span><span>O型血</span>","randListTag":"<span>租房</span><span>属猪</span><span>O型血</span><span>白羊座</span>","userIcon":"<i title=在线 class=online></i><i title=手机认证 class=tel></i>","helloUrl":"http://www.jiayuan.com/msg/hello.php?type=20&randomfrom=4&uhash=5463c9cd025182fbde91179e491cbeaa","sendMsgUrl":"http://www.jiayuan.com/msg/send.php?uhash=5463c9cd025182fbde91179e491cbeaa","shortnote":"你不用很好  我喜欢就好  我没有多好  你不嫌弃就好...","matchCondition":"32-39岁,171-190cm,大专以上,有照片,未婚,广东,惠州"},{"uid":147846345,"realUid":148846345,"nickname":"prejudice","sex":"女","sexValue":"f","randAttr":"formal","marriage":"未婚","height":"160","education":"本科","income":null,"work_location":"珠海","work_sublocation":"珠海","age":28,"image":"http://at1.jyimg.com/46/60/aq0b0519554443d1b1bcd4d17bae/ad0b05195_12_avatar_p.jpg","count":"95243","online":1,"randTag":"<span>有车</span><span>本科</span>","randListTag":"<span>有车</span><span>属马</span><span>未婚</span><span>金牛座</span>","userIcon":"<i title=在线 class=online></i><i title=手机认证 class=tel></i>","helloUrl":"http://www.jiayuan.com/msg/hello.php?type=20&randomfrom=4&uhash=46ad0b0519554443d1b1bcd4d17bae60","sendMsgUrl":"http://www.jiayuan.com/msg/send.php?uhash=46ad0b0519554443d1b1bcd4d17bae60","shortnote":"是的，我很不想来这里但是还是来了。年龄越大就越独立和勇敢自信，越优秀就越找不到适合的男生了。我有房子车子，也有很好很稳定的工作和不错收入。希望可以遇到一个和我一样优秀或者比我优秀的…","matchCondition":"28-40岁,175-185cm,本科,有照片,未婚,广东,珠海"},{"uid":147870133,"realUid":148870133,"nickname":"happy1314","sex":"女","sexValue":"f","randAttr":"formal","marriage":"离异","height":"158","education":"大专","income":null,"work_location":"深圳","work_sublocation":"深圳","age":40,"image":"http://at4.jyimg.com/32/da/e845c3c35d27fe3c4d31c9ee8154/e845c3c35_4_avatar_p.jpg","count":"95243","online":1,"randTag":"<span>汉族</span><span>天秤座</span>","randListTag":"<span>属马</span><span>158cm</span><span>汉族</span><span>大专</span>","userIcon":"<i title=在线 class=online></i><i title=手机认证 class=tel></i>","helloUrl":"http://www.jiayuan.com/msg/hello.php?type=20&randomfrom=4&uhash=32e845c3c35d27fe3c4d31c9ee8154da","sendMsgUrl":"http://www.jiayuan.com/msg/send.php?uhash=32e845c3c35d27fe3c4d31c9ee8154da","shortnote":"我只想找一份简单，真诚，忠诚的婚姻！ 没有欺骗，没有谎言的感情！                                   脾气不要太暴躁了，心胸宽阔，性格开朗！心地善良…","matchCondition":"37-45岁,158-183cm,大专,有照片,香港,香港"},{"uid":147907777,"realUid":148907777,"nickname":"靓靓","sex":"女","sexValue":"f","randAttr":"formal","marriage":"离异","height":"162","education":"大专","income":null,"work_location":"广州","work_sublocation":"广州","age":40,"image":"http://at1.jyimg.com/85/df/899fc457b468f4977c1a82f851b9/899fc457b_4_avatar_p.jpg","count":"95243","online":1,"randTag":"<span>162cm</span><span>汉族</span>","randListTag":"<span>162cm</span><span>50公斤</span><span>大专</span><span>魔羯座</span>","userIcon":"<i title=在线 class=online></i><i title=手机认证 class=tel></i>","helloUrl":"http://www.jiayuan.com/msg/hello.php?type=20&randomfrom=4&uhash=85899fc457b468f4977c1a82f851b9df","sendMsgUrl":"http://www.jiayuan.com/msg/send.php?uhash=85899fc457b468f4977c1a82f851b9df","shortnote":"希望能在佳缘遇到一份真挚的感情。期待有缘人，共同携手人生漫漫长路。相儒以沫，不离不弃。本人相片均为近照，资料真实。祝天下有情人终成眷属！......","matchCondition":"45-55岁,170-180cm,有照片,广东"},{"uid":147854574,"realUid":148854574,"nickname":"无恙","sex":"女","sexValue":"f","randAttr":"formal","marriage":"未婚","height":"160","education":"本科","income":null,"work_location":"深圳","work_sublocation":"深圳","age":33,"image":"http://at1.jyimg.com/cc/18/3fd7520a7489fb0b6cf62c57e085/3fd7520a7_4_avatar_p.jpg","count":"95243","online":1,"randTag":"<span>汉族</span><span>魔羯座</span>","randListTag":"<span>属狗</span><span>160cm</span><span>50公斤</span><span>O型血</span>","userIcon":"<i title=在线 class=online></i><i title=聊天包月 class=ltby></i>","helloUrl":"http://www.jiayuan.com/msg/hello.php?type=20&randomfrom=4&uhash=cc3fd7520a7489fb0b6cf62c57e08518","sendMsgUrl":"http://www.jiayuan.com/msg/send.php?uhash=cc3fd7520a7489fb0b6cf62c57e08518","shortnote":"人生就像风一样，飘过就不再回来，人世间，所有的事，苦也好，甜也好，都是一种缘分，一种不期而遇，上天给予我们的，我们欣然地接受，看淡了苦，淡然了累，生活依然很美好......","matchCondition":"33-42岁,168-180cm,大专以上,广东,深圳"},{"uid":147857568,"realUid":148857568,"nickname":"等待幸福的港湾","sex":"女","sexValue":"f","randAttr":"formal","marriage":"离异","height":"160","education":"本科","income":null,"work_location":"深圳","work_sublocation":"深圳","age":45,"image":"http://at2.jyimg.com/97/23/f30fed8c215ccfc98c2116e98be1/f30fed8c2_1_avatar_p.jpg","count":"95243","online":1,"randTag":"<span>属牛</span><span>本科</span>","randListTag":"<span>属牛</span><span>160cm</span><span>本科</span><span>白羊座</span>","userIcon":"<i title=在线 class=online></i><i title=手机认证 class=tel></i>","helloUrl":"http://www.jiayuan.com/msg/hello.php?type=20&randomfrom=4&uhash=97f30fed8c215ccfc98c2116e98be123","sendMsgUrl":"http://www.jiayuan.com/msg/send.php?uhash=97f30fed8c215ccfc98c2116e98be123","shortnote":"快乐的日子，总是令人期待。美好的踪影，正在不远的地方，轻轻召唤，我从千里之外，遍寻你的足迹，只为了合上你的节拍，与你共度此生。","matchCondition":"42-55岁,160-175cm,有照片,广东,深圳"},{"uid":147811300,"realUid":148811300,"nickname":"平平","sex":"女","sexValue":"f","randAttr":"formal","marriage":"离异","height":"156","education":"高中中专及以下","income":null,"work_location":"东莞","work_sublocation":"东莞","age":38,"image":"http://at2.jyimg.com/df/99/c8002d484cb9bd4a483c999795e6/c8002d484_1_avatar_p.jpg","count":"95243","online":0,"randTag":"<span>汉族</span><span>O型血</span>","randListTag":"<span>汉族</span><span>中专</span><span>O型血</span><span>狮子座</span>","userIcon":"<i title=手机认证 class=tel></i><i title=看信包月 class=kxby></i>","helloUrl":"http://www.jiayuan.com/msg/hello.php?type=20&randomfrom=4&uhash=dfc8002d484cb9bd4a483c999795e699","sendMsgUrl":"http://www.jiayuan.com/msg/send.php?uhash=dfc8002d484cb9bd4a483c999795e699","shortnote":"有一种爱，长久且让人心醉，有一种情，伤人且自伤。有一种蛊被称为一味相思，让人不由沉醉且相思入骨。爱情就是两个人在一起不离不弃，执子之手，与子偕老；爱情是无私的给予，没有任何条件；爱…","matchCondition":"38-49岁,170-185cm,有照片,离异,广东,东莞"},{"uid":147695488,"realUid":148695488,"nickname":"真善美","sex":"女","sexValue":"f","randAttr":"formal","marriage":"离异","height":"167","education":"本科","income":null,"work_location":"东莞","work_sublocation":"东莞","age":42,"image":"http://at3.jyimg.com/2d/bb/6814e6df1663157b929cb7838797/6814e6df1_1_avatar_p.jpg","count":"95243","online":0,"randTag":"<span>属龙</span><span>167cm</span>","randListTag":"<span>属龙</span><span>65公斤</span><span>汉族</span><span>O型血</span>","userIcon":","helloUrl":"http://www.jiayuan.com/msg/hello.php?type=20&randomfrom=4&uhash=2d6814e6df1663157b929cb7838797bb","sendMsgUrl":"http://www.jiayuan.com/msg/send.php?uhash=2d6814e6df1663157b929cb7838797bb","shortnote":"周一到周五的上班族，是个善良温和的人，喜欢读书，音乐，旅行，美食和运动。希望找到一个能聊天聊地，志同道合的乐观向上之人,一起慢慢变老。。。(更正一下，本人属蛇，与属相为鸡、猴、牛的…","matchCondition":"44-48岁,173-182cm,有照片,广东,东莞"},{"uid":147709157,"realUid":148709157,"nickname":"佛系人生","sex":"女","sexValue":"f","randAttr":"formal","marriage":"未婚","height":"155","education":"高中中专及以下","income":null,"work_location":"深圳","work_sublocation":"深圳","age":22,"image":"http://images1.jyimg.com/w4/global/i/yzphykj_f.jpg","count":"95243","online":1,"randTag":"<span>属鼠</span><span>汉族</span>","randListTag":"<span>汉族</span><span>未婚</span><span>中专</span><span>双子座</span>","userIcon":"<i title=在线 class=online></i><i title=手机认证 class=tel></i>","helloUrl":"http://www.jiayuan.com/msg/hello.php?type=20&randomfrom=4&uhash=eb8836196709d862ee5c1c1660b26abf","sendMsgUrl":"http://www.jiayuan.com/msg/send.php?uhash=eb8836196709d862ee5c1c1660b26abf","shortnote":"被动型 希望对方成熟稳重 有上进心 很讨厌男孩子抽烟 喝酒打牌 玩游戏 我颜控   我是个160斤的胖纸，胖纸胖纸胖纸，重要的事要讲三遍，看清读白再发信，谢谢......","matchCondition":"25-30岁,175-不限 cm,有照片,未婚,广东,深圳"},{"uid":147724766,"realUid":148724766,"nickname":"童吉","sex":"女","sexValue":"f","randAttr":"formal","marriage":"离异","height":"166","education":"本科","income":null,"work_location":"深圳","work_sublocation":"深圳","age":39,"image":"http://at3.jyimg.com/e0/aa/3d33a8118d44bd824d6ca4aa5899/3d33a8118_2_avatar_p.jpg","count":"95243","online":1,"randTag":"<span>属羊</span><span>166cm</span>","randListTag":"<span>有房</span><span>166cm</span><span>本科</span><span>天蝎座</span>","userIcon":"<i title=在线 class=online></i><i title=手机认证 class=tel></i>","helloUrl":"http://www.jiayuan.com/msg/hello.php?type=20&randomfrom=4&uhash=e03d33a8118d44bd824d6ca4aa5899aa","sendMsgUrl":"http://www.jiayuan.com/msg/send.php?uhash=e03d33a8118d44bd824d6ca4aa5899aa","shortnote":"我是一个正直,乐观,孝顺的人 ，我现在的生活状态和心情，可以说是“静待缘分”。","matchCondition":"36-44岁,166-191cm,广东,深圳"},{"uid":147671033,"realUid":148671033,"nickname":"冷銫調.","sex":"女","sexValue":"f","randAttr":"formal","marriage":"未婚","height":"166","education":"硕士","income":null,"work_location":"广州","work_sublocation":"广州","age":32,"image":"http://images1.jyimg.com/w4/global/i/yzphykj_f.jpg","count":"95243","online":0,"randTag":"<span>汉族</span><span>硕士</span>","randListTag":"<span>属虎</span><span>166cm</span><span>汉族</span><span>未婚</span>","userIcon":"<i title=手机认证 class=tel></i>","helloUrl":"http://www.jiayuan.com/msg/hello.php?type=20&randomfrom=4&uhash=0f02a20610771a8ad3432e2bfbccf0a8","sendMsgUrl":"http://www.jiayuan.com/msg/send.php?uhash=0f02a20610771a8ad3432e2bfbccf0a8","shortnote":"注明：现在我只能看免费信，看到有些信件没能打开。对于无法打开的信件，恕不回复。    86年出生，1米66，53公斤，硕士毕业，在广州工作，喜欢自己的工作。性格开朗、善良、不失幽默…","matchCondition":"31-35岁,170-177cm,本科,有照片,未婚,广东,广州"}],"second_search":0,"express_search":[{"uid":"31853009","realUid":32853009,"sex":"m","nickname":"Alen","helloUrl":"http://www.jiayuan.com/msg/hello.php?type=20&randomfrom=4&uhash=d829acd08580c41e92102b08f69e9087","age":36,"image":"http://at2.jyimg.com/d8/87/29acd08580c41e92102b08f69e90/29acd0858_3_avatar_p.jpg","work_location":"广东","ex_mark":"有房","fxly":"cp-eexpress"},{"uid":"117162304","realUid":118162304,"sex":"m","nickname":"幸福~生活","helloUrl":"http://www.jiayuan.com/msg/hello.php?type=20&randomfrom=4&uhash=a358aeed99a92c5a0fd45a6f39c6b4ab","age":44,"image":"http://at3.jyimg.com/a3/ab/58aeed99a92c5a0fd45a6f39c6b4/58aeed99a_3_avatar_p.jpg","work_location":"广东","ex_mark":"高收入","fxly":"cp-eexpress"},{"uid":"110086505","realUid":111086505,"sex":"m","nickname":"<font >ba</font>by_Anne","helloUrl":"http://www.jiayuan.com/msg/hello.php?type=20&randomfrom=4&uhash=ec7f934f23ceacde016c21be7b7d7637","age":42,"image":"http://at3.jyimg.com/ec/37/7f934f23ceacde016c21be7b7d76/7f934f23c_16_avatar_p.jpg","work_location":"广东","ex_mark":"有房","fxly":"cp-eexpress"},{"uid":"171913548","realUid":172913548,"sex":"m","nickname":"Andy","helloUrl":"http://www.jiayuan.com/msg/hello.php?type=20&randomfrom=4&uhash=f45cfa990d8e84e5830fa30dcbad0ba7","age":35,"image":"http://at4.jyimg.com/f4/a7/5cfa990d8e84e5830fa30dcbaq0b/5cfa990d8_1_avatar_p.jpg","work_location":"广东","ex_mark":"有喂,要幸福房","fxly":"cp-eexpress"},{"uid":"74324568","realUid":75324568,"sex":"m","nickname":"风继续吹","helloUrl":"http://www.jiayuan.com/msg/hello.php?type=20&randomfrom=4&uhash=efd68106055fc90d363e31bfb8c09a34","age":37,"image":"http://at3.jyimg.com/ef/34/d68106055fc90d363e31bfb8c09a/d68106055_17_avatar_p.jpg","work_location":"广东","ex_mark":"有房","fxly":"cp-eexpress"}],"condi":{"work_sublocation":[],"work_location":["44"],"avatar":"1"}}